py_modular/__init__.py
py_modular/effects/__init__.py
py_modular/effects/dsp.py
py_modular/effects/mixer.py
py_modular/effects/processing.py
py_modular/generative/__init__.py
py_modular/generative/utils.py
py_modular/models/__init__.py
py_modular/models/synths.py
py_modular/sound/__init__.py
py_modular/sound/granular.py
py_modular/sound/oscillators.py
py_modular/time/__init__.py
py_modular/time/envelopes.py
py_modular/time/events.py
py_modular/time/transport.py
py_modular/utils/__init__.py
py_modular/utils/debug.py
py_modular/utils/processing.py
py_modular-0.0.1.dist-info/LICENSE
py_modular-0.0.1.dist-info/METADATA
py_modular-0.0.1.dist-info/WHEEL
py_modular-0.0.1.dist-info/top_level.txt
py_modular-0.0.1.dist-info/RECORD
