Metadata-Version: 2.1
Name: py-modular
Version: 0.0.1
Summary: An experimental, modular audio programming environment in python
Home-page: https://github.com/fredyeah/py-modular
Author: Frederic
Author-email: mark.s@catalyst-students.com
License: UNKNOWN
Platform: UNKNOWN
Classifier: Programming Language :: Python :: 3
Classifier: License :: OSI Approved :: MIT License
Classifier: Operating System :: OS Independent
Requires-Dist: cffi
Requires-Dist: cycler
Requires-Dist: kiwisolver
Requires-Dist: matplotlib
Requires-Dist: numpy
Requires-Dist: Pillow
Requires-Dist: pycparser
Requires-Dist: pyparsing
Requires-Dist: python-dateutil
Requires-Dist: six
Requires-Dist: sounddevice
Requires-Dist: SoundFile
